{
  "type": "FeatureCollection",
  "features": [
    {
      "type": "Feature",
      "geometry": {
        "type": "Point",
        "coordinates": [
          -93.541,
          34.3689
        ]
      },
      "properties": {
        "id": "AR-001",
        "name": "Arkansas Dispersed 1",
        "type": "dispersed",
        "cost": 0,
        "rating": null,
        "reviews_count": 0,
        "amenities": [],
        "rig_friendly": [],
        "road_difficulty": "dirt",
        "state": "AR",
        "source": "generated"
      }
    },
    {
      "type": "Feature",
      "geometry": {
        "type": "Point",
        "coordinates": [
          -91.353,
          36.3365
        ]
      },
      "properties": {
        "id": "AR-002",
        "name": "Arkansas Dispersed 2",
        "type": "dispersed",
        "cost": 0,
        "rating": null,
        "reviews_count": 0,
        "amenities": [
          "water"
        ],
        "rig_friendly": [],
        "road_difficulty": "dirt",
        "state": "AR",
        "source": "generated"
      }
    },
    {
      "type": "Feature",
      "geometry": {
        "type": "Point",
        "coordinates": [
          -93.5235,
          36.1181
        ]
      },
      "properties": {
        "id": "AR-003",
        "name": "Arkansas Dispersed 3",
        "type": "dispersed",
        "cost": 0,
        "rating": null,
        "reviews_count": 0,
        "amenities": [],
        "rig_friendly": [],
        "road_difficulty": "gravel",
        "state": "AR",
        "source": "generated"
      }
    },
    {
      "type": "Feature",
      "geometry": {
        "type": "Point",
        "coordinates": [
          -93.4439,
          34.8964
        ]
      },
      "properties": {
        "id": "AR-004",
        "name": "Arkansas Campground 4",
        "type": "established",
        "cost": 30,
        "rating": "4.3",
        "reviews_count": 28,
        "amenities": [
          "water",
          "toilets",
          "picnic_tables"
        ],
        "rig_friendly": [
          "tent",
          "RV"
        ],
        "road_difficulty": "gravel",
        "state": "AR",
        "source": "generated"
      }
    },
    {
      "type": "Feature",
      "geometry": {
        "type": "Point",
        "coordinates": [
          -93.729,
          34.85
        ]
      },
      "properties": {
        "id": "AR-005",
        "name": "Arkansas Campground 5",
        "type": "established",
        "cost": 0,
        "rating": "4.9",
        "reviews_count": 40,
        "amenities": [
          "fire_rings",
          "toilets",
          "water",
          "showers",
          "picnic_tables"
        ],
        "rig_friendly": [],
        "road_difficulty": "paved",
        "state": "AR",
        "source": "generated"
      }
    },
    {
      "type": "Feature",
      "geometry": {
        "type": "Point",
        "coordinates": [
          -93.8868,
          34.5662
        ]
      },
      "properties": {
        "id": "AR-006",
        "name": "Arkansas Backcountry 6",
        "type": "backcountry",
        "cost": 0,
        "rating": "3.9",
        "reviews_count": 22,
        "amenities": [],
        "rig_friendly": [],
        "road_difficulty": "gravel",
        "state": "AR",
        "source": "generated"
      }
    }
  ]
}